googlewrapper/__init__.py
googlewrapper/cal.py
googlewrapper/connect.py
googlewrapper/docs.py
googlewrapper/ga.py
googlewrapper/gbq.py
googlewrapper/gsc.py
googlewrapper/pagespeed.py
googlewrapper/py.typed
googlewrapper/reports.py
googlewrapper/sheets.py
googlewrapper-0.2.11.dist-info/LICENSE
googlewrapper-0.2.11.dist-info/METADATA
googlewrapper-0.2.11.dist-info/WHEEL
googlewrapper-0.2.11.dist-info/top_level.txt
googlewrapper-0.2.11.dist-info/RECORD
