Metadata-Version: 2.1
Name: googlewrapper
Version: 0.2.11
Summary: Simple API wrapper for Google Products
Home-page: https://github.com/jaceiverson/googlewrapper
Author: Jace Iverson
License: MIT
Project-URL: Bug Tracker, https://github.com/jaceiverson/googlewrapper/issues
Keywords: google,api,wrapper,search console,analytics,big query,sheets,docs,pagespeed,gmail,calendar,gsc,ga,gbq,report
Platform: unix
Platform: linux
Platform: osx
Platform: cygwin
Platform: win32
Classifier: Programming Language :: Python :: 3
Requires-Python: >=3.9
License-File: LICENSE
Requires-Dist: google-api-python-client (==2.4.0)
Requires-Dist: oauth2client (==4.1.3)
Requires-Dist: pandas (==1.4.4)
Requires-Dist: pygsheets (==2.0.5)
Requires-Dist: google-cloud-bigquery (==3.3.0)
Requires-Dist: pandas-gbq (==0.17.8)
Requires-Dist: pdcompare (==0.1.5)
Provides-Extra: testing
Requires-Dist: pytest (>=6.0) ; extra == 'testing'
Requires-Dist: pytest-cov (>=2.0) ; extra == 'testing'
Requires-Dist: mypy (>=0.910) ; extra == 'testing'
Requires-Dist: flake8 (>=3.9) ; extra == 'testing'
Requires-Dist: tox (>=3.24) ; extra == 'testing'
